pysharpen/__init__.py
pysharpen/__version__.py
pysharpen/pysharpen.py
pysharpen/worker.py
pysharpen/functional/__init__.py
pysharpen/functional/brightness_adjustment.py
pysharpen/functional/dtype_utils.py
pysharpen/functional/type_conversion.py
pysharpen/methods/__init__.py
pysharpen/methods/img_proc.py
pysharpen/methods/preprocessing/__init__.py
pysharpen/methods/preprocessing/brightness.py
pysharpen/methods/preprocessing/gamma.py
pysharpen/methods/sharpening/__init__.py
pysharpen/methods/sharpening/brovey.py
pysharpen/methods/sharpening/gihs.py
pysharpen/methods/sharpening/ihs.py
pysharpen-0.2.8.dist-info/LICENSE
pysharpen-0.2.8.dist-info/METADATA
pysharpen-0.2.8.dist-info/WHEEL
pysharpen-0.2.8.dist-info/entry_points.txt
pysharpen-0.2.8.dist-info/top_level.txt
pysharpen-0.2.8.dist-info/RECORD
