Metadata-Version: 2.1
Name: pysharpen
Version: 0.2.8
Summary: Remote sensing image pansharpening and enhancement.
Home-page: https://github.com/AlexeyTrekin/pansharpen
Author: Alexey Trekin
Author-email: alexey.trekin@gmail.com
License: MIT
Platform: UNKNOWN
Classifier: License :: OSI Approved :: MIT License
Classifier: Programming Language :: Python
Classifier: Programming Language :: Python :: 3
Classifier: Programming Language :: Python :: Implementation :: CPython
Classifier: Programming Language :: Python :: Implementation :: PyPy
Requires-Python: >=3.4.0
Requires-Dist: aeronet (>=0.0.8)
Requires-Dist: click (>=6.7)
Provides-Extra: tests
Requires-Dist: pytest ; extra == 'tests'
